{
  "category": "plants/exotic-with-botanical",
  "name": "N/A",
  "description": "Eryngium paniculatum is a plant endemic to the southern half of Chile all the way down to Tierra del Fuego and it is also found in Argentina. This plant is noted for being aggressive in its native habitat and livestock grazing pastures.<br>Eryngium paniculatum is an evergreen, rosette forming herbaceous perennial with tall erect flowering stems. It has green, strap-shaped leaves that have margins of fine spines resembling a Puya. The leaves are &gt;30 cm long and 3 cm wide and are arranged in a rosette.<br>Its flowering stems which grow &gt;1.5 m in height are green and erect, branching towards the top. Its white-green flowers are spherical, are up to 3cm across and appear in a branched racemose inflorescence. The flower heads are followed by numerous viable seeds. Its roots are rhizomes.<br><br><a href=\"http://ketenewplymouth.peoplesnetworknz.info/image_files/0000/0012/5733/Eryngium_paniculatum.JPG\" target=\"_blank\"><img src=\"http://ketenewplymouth.peoplesnetworknz.info/image_files/0000/0012/5733/Eryngium_paniculatum.JPG\" alt=\"\" width=\"100%\" height=\"auto\"></a><br></p> <p><a href=\"http://ketenewplymouth.peoplesnetworknz.info/image_files/0000/0012/5738/Eryngium_paniculatum-002.JPG\" target=\"_blank\"><img src=\"http://ketenewplymouth.peoplesnetworknz.info/image_files/0000/0012/5738/Eryngium_paniculatum-002.JPG\" alt=\"\" width=\"100%\" height=\"auto\"></a><br><br><a href=\"http://ketenewplymouth.peoplesnetworknz.info/image_files/0000/0012/5743/Eryngium_paniculatum-003.JPG\" target=\"_blank\"><img src=\"http://ketenewplymouth.peoplesnetworknz.info/image_files/0000/0012/5743/Eryngium_paniculatum-003.JPG\" alt=\"\" width=\"100%\" height=\"auto\"></a></p> <p>Thanks to Wikipedia for text and information <a href=\"http://creativecommons.org/licenses/by-sa/3.0/\" target=\"_blank\">http://creativecommons.org/licenses/by-sa/3.0/</a></p> <br style=\"clear:both;\"> <div class=\"hr\"> </div> ",
  "attributes": [
    {
      "key": "Kingdom",
      "value": "Plantae"
    },
    {
      "key": "Phylum",
      "value": "Magnoliophyta"
    },
    {
      "key": "Class",
      "value": "Magnoliopsida"
    },
    {
      "key": "Order",
      "value": "Apiales"
    },
    {
      "key": "Family",
      "value": "Apiaceae"
    },
    {
      "key": "Genus",
      "value": "Saniculoideae"
    },
    {
      "key": "Tribes",
      "value": "Saniculeae"
    },
    {
      "key": "Genus",
      "value": "Eryngium"
    },
    {
      "key": "Species",
      "value": "E. paniculatum"
    },
    {
      "key": "Binominal name",
      "value": "Eryngium paniculatum"
    },
    {
      "key": "Synonyms",
      "value": "Eryngium paniculatum var. atrocephalum, Eryngium paniculatum var. chilense, Eryngium paniculatum f. junior, Eryngium paniculatum var. litorale, Eryngium subulatum"
    },
    {
      "key": "Common names",
      "value": "Sea Holly, Chupalla, Caraguatá, Cadilla,"
    }
  ],
  "images": [
    {
      "src": "http://ketenewplymouth.peoplesnetworknz.info/image_files/0000/0012/5733/Eryngium_paniculatum.JPG",
      "caption": ""
    },
    {
      "src": "http://ketenewplymouth.peoplesnetworknz.info/image_files/0000/0012/5738/Eryngium_paniculatum-002.JPG",
      "caption": ""
    },
    {
      "src": "http://ketenewplymouth.peoplesnetworknz.info/image_files/0000/0012/5743/Eryngium_paniculatum-003.JPG",
      "caption": ""
    }
  ]
}