{
  "category": "plants/trees/trees-native",
  "name": "N/A",
  "description": "Coprosma aff.neglecta whangaroa is a gently mounding shrub and is one of a number of closely related forms that grow in far-flung parts of Northland’s coastline. It is endemic to the base of andesite breccia cliffs on the northern side Whangaroa Harbour and in Pekapeka Bay a small islet on the just inside the harbour entrance.<br>Coprosma 'Whangaroa' grows to about 1+ m tall and has elongated, ascending stems. Its small, dark green leaves are oval or spherical in shape.<br>It is dioecious meaning it has male and female flowers on separate plants. The male and female flowers develop on the branchlets during spring. The female flower has two long cream stigmas, while the male flower has four filaments that are each topped with an anther.<br>About April the female plants produce 5-6 mm dupes that are a dark red or black in colour. They each contain 2 seeds.<br><br><img src=\"http://ketenewplymouth.peoplesnetworknz.info/image_files/0000/0009/3243/coprosma_neglecta_whangaroa.jpg\" alt=\"\" width=\"100%\" height=\"auto\"><br><br>Thanks to Wikipedia for text and information <a href=\"http://creativecommons.org/licenses/by-sa/3.0/\" target=\"_blank\">http://creativecommons.org/licenses/by-sa/3.0/</a><br><br></p> <br style=\"clear:both;\"> <div class=\"hr\"> </div> ",
  "attributes": [
    {
      "key": "Kingdom",
      "value": "Plantae"
    },
    {
      "key": "Clade",
      "value": "Angiosperms"
    },
    {
      "key": "Clade",
      "value": "Eudicots"
    },
    {
      "key": "Clade",
      "value": "Asterids"
    },
    {
      "key": "Order",
      "value": "Gentianales"
    },
    {
      "key": "Family",
      "value": "Rubiaceae"
    },
    {
      "key": "Subfamily",
      "value": "Rubioideae"
    },
    {
      "key": "Tribe",
      "value": "Anthospermeae"
    },
    {
      "key": "Genus",
      "value": "Coprosma"
    },
    {
      "key": "Species",
      "value": "C. neglecta"
    },
    {
      "key": "Subspecies",
      "value": "\"Whangaroa\""
    },
    {
      "key": "Scientific name",
      "value": "Coprosma aff.neglecta whangaroa"
    },
    {
      "key": "Common name",
      "value": "Coprosma 'Whangaroa'."
    }
  ],
  "images": [
    {
      "src": "http://ketenewplymouth.peoplesnetworknz.info/image_files/0000/0009/3243/coprosma_neglecta_whangaroa.jpg",
      "caption": ""
    }
  ]
}